dilawar/__init__.py
dilawar/audio/filter.py
dilawar/audio/spectrogram.py
dilawar/bin/pandoc-gls.py
dilawar/bin/pandoc-quantity.py
dilawar/brian_utils.py
dilawar/brian_utils.py.png
dilawar/core.py
dilawar/data_analysis.py
dilawar/file_utils.py
dilawar/functions.py
dilawar/hopfield.py
dilawar/information_theory.py
dilawar/io_utils.py
dilawar/logger.py
dilawar/matplotlib_basic_units.py
dilawar/md2html.py
dilawar/md2pdf.py
dilawar/nx_utils.py
dilawar/pandoc/__init__.py
dilawar/pandoc/__main__.py
dilawar/pandoc/longtable_solution_twocol.tex
dilawar/pandoc/pandoc.css
dilawar/pandoc/plantuml.py
dilawar/pandoc/preprocess_of_docx.py
dilawar/pandoc/templates/default.beamer
dilawar/pandoc/templates/default.latex
dilawar/pandoc/test.pandoc
dilawar/pandoc/tikz.py
dilawar/pandoc/utils.py
dilawar/plot_utils.py
dilawar/plot_utils.py.png
dilawar/statistics.py
dilawar/text_processing.py
dilawar-0.9.0.dist-info/WHEEL
dilawar-0.9.0.dist-info/METADATA
dilawar-0.9.0.dist-info/RECORD
