Metadata-Version: 2.1
Name: dilawar
Version: 0.9.0
Summary: Personal collection of utilities
License: GPLv3
Author: Dilawar Singh
Author-email: dilawar.s.rajput@gmail.com
Requires-Python: >=3.7.1,<3.10
Classifier: License :: Other/Proprietary License
Classifier: Programming Language :: Python :: 3
Classifier: Programming Language :: Python :: 3.8
Classifier: Programming Language :: Python :: 3.9
Requires-Dist: Pint (>=0.17,<0.18)
Requires-Dist: colorama (>=0.4.4,<0.5.0)
Requires-Dist: matplotlib (>=3.4.2,<4.0.0)
Requires-Dist: networkx (>=2.5.1,<3.0.0)
Requires-Dist: numpy (>=1.20.3,<2.0.0)
Requires-Dist: pandocfilters (>=1.4.3,<2.0.0)
Requires-Dist: panflute (>=2.1.0,<3.0.0)
Requires-Dist: pydot[graph] (>=1.4.2,<2.0.0)
Requires-Dist: pygraphviz[graph] (>=1.7,<2.0)
Requires-Dist: pypandoc (>=1.5,<2.0)
